dpgcontainers/__init__.py
dpgcontainers/base.py
dpgcontainers/containers.py
dpgcontainers/exceptions.py
dpgcontainers/py.typed
dpgcontainers-0.1.10.dist-info/METADATA
dpgcontainers-0.1.10.dist-info/WHEEL
dpgcontainers-0.1.10.dist-info/licenses/LICENSE.md
dpgcontainers-0.1.10.dist-info/RECORD
