Metadata-Version: 2.4
Name: dpgcontainers
Version: 0.1.10
Summary: Functional dataclass implementations for DearPyGUI container types
Author-email: Zachary Parmley <zachary.parmley@gmail.com>
License-File: LICENSE.md
Classifier: License :: OSI Approved :: MIT License
Classifier: Operating System :: OS Independent
Classifier: Programming Language :: Python :: 3
Classifier: Topic :: Software Development :: User Interfaces
Requires-Python: >=3.13
Requires-Dist: dearpygui>=2.0.0
Requires-Dist: dpgmagictag>=0.1.0
